{
  "symbol": "GBTC",
  "name": "Grayscale Bitcoin Trust ETF",
  "last_updated": "2025-12-03T07:50:50.332Z",
  "profile": {
    "name": "Grayscale Bitcoin Trust ETF",
    "issuer": "Digital Currency Group, Inc.",
    "brand": "Grayscale",
    "structure": "ETF",
    "expense_ratio": 0.015,
    "inception_date": "Jan 11, 2024",
    "index_tracked": "CME CF Benchmarks Bitcoin Reference Rate-New York Variant",
    "home_page": "https://etfs.grayscale.com/gbtc",
    "category": "Currency",
    "asset_class": "Currency",
    "region_general": "Global",
    "region_specific": "Broad",
    "aum": 15300300000,
    "shares_outstanding": 214400000
  },
  "holdings": [
    {
      "symbol": "US DOLLAR",
      "name": "U.S. Dollar",
      "weight": 100
    }
  ]
}
