{
  "symbol": "IUSG",
  "last_updated": "2025-12-01T08:26:19.566Z",
  "profile": {
    "issuer": "BlackRock, Inc.",
    "brand": "iShares",
    "structure": "ETF",
    "expense_ratio": 0.0004,
    "inception_date": "Jul 24, 2000",
    "index_tracked": "S&P 900 Growth",
    "home_page": "https://www.ishares.com/us/products/239713/ishares-russell-3000-growth-etf",
    "category": "Large Cap Growth Equities",
    "asset_class": "Equity",
    "asset_class_size": "Large-Cap",
    "asset_class_style": "Growth",
    "region_general": "North America",
    "region_specific": "U.S.",
    "aum": 25876900000,
    "shares_outstanding": 155300000
  },
  "holdings": [
    {
      "symbol": "NVDA",
      "name": "NVIDIA Corporation",
      "weight": 13.14
    },
    {
      "symbol": "AAPL",
      "name": "Apple Inc.",
      "weight": 5.66
    },
    {
      "symbol": "MSFT",
      "name": "Microsoft Corporation",
      "weight": 5.6
    },
    {
      "symbol": "AVGO",
      "name": "Broadcom Inc.",
      "weight": 5.59
    },
    {
      "symbol": "GOOGL",
      "name": "Alphabet Inc. Class A",
      "weight": 5.56
    },
    {
      "symbol": "GOOG",
      "name": "Alphabet Inc. Class C",
      "weight": 4.47
    },
    {
      "symbol": "META",
      "name": "Meta Platforms Inc Class A",
      "weight": 4.1
    },
    {
      "symbol": "AMZN",
      "name": "Amazon.com, Inc.",
      "weight": 3.85
    },
    {
      "symbol": "TSLA",
      "name": "Tesla, Inc.",
      "weight": 3.58
    },
    {
      "symbol": "LLY",
      "name": "Eli Lilly and Company",
      "weight": 2.62
    },
    {
      "symbol": "V",
      "name": "Visa Inc. Class A",
      "weight": 1.69
    },
    {
      "symbol": "JPM",
      "name": "JPMorgan Chase & Co.",
      "weight": 1.44
    },
    {
      "symbol": "BRK.B",
      "name": "Berkshire Hathaway Inc. Class B",
      "weight": 1.37
    },
    {
      "symbol": "NFLX",
      "name": "Netflix, Inc.",
      "weight": 1.35
    },
    {
      "symbol": "MA",
      "name": "Mastercard Incorporated Class A",
      "weight": 1.34
    }
  ]
}